lanro_gym/VERSION
lanro_gym/__init__.py
lanro_gym/language_utils.py
lanro_gym/simulation.py
lanro_gym/utils.py
lanro_gym/env/__init__.py
lanro_gym/env/base.py
lanro_gym/env/goal.py
lanro_gym/env/language.py
lanro_gym/env_utils/__init__.py
lanro_gym/env_utils/object_properties.py
lanro_gym/env_utils/task_object.py
lanro_gym/env_utils/task_object_list.py
lanro_gym/environments/__init__.py
lanro_gym/environments/panda.py
lanro_gym/environments/panda_nl.py
lanro_gym/robots/__init__.py
lanro_gym/robots/panda.py
lanro_gym/robots/pybrobot.py
lanro_gym/tasks/__init__.py
lanro_gym/tasks/nlgrasp.py
lanro_gym/tasks/nllift.py
lanro_gym/tasks/nlpush.py
lanro_gym/tasks/nlreach.py
lanro_gym/tasks/push.py
lanro_gym/tasks/reach.py
lanro_gym/tasks/scene.py
lanro_gym/tasks/slide.py
lanro_gym/tasks/stack.py
lanro_gym/tasks/core/__init__.py
lanro_gym/tasks/core/language_task.py
lanro_gym/tasks/core/task.py
lanro_gym-0.2.1.dist-info/LICENSE
lanro_gym-0.2.1.dist-info/METADATA
lanro_gym-0.2.1.dist-info/WHEEL
lanro_gym-0.2.1.dist-info/top_level.txt
lanro_gym-0.2.1.dist-info/RECORD
