Metadata-Version: 2.1
Name: lanro-gym
Version: 0.2.1
Summary: Gymnasium multi-goal environments for goal-conditioned and language-conditioned deep reinforcement learning build with PyBullet
Home-page: https://github.com/frankroeder/lanro-gym
Author: Frank Röder
Author-email: frank.roeder@tuhh.de
License: MIT
Classifier: Operating System :: OS Independent
Classifier: License :: OSI Approved :: MIT License
Classifier: Programming Language :: Python :: 3.7
Classifier: Programming Language :: Python :: 3.8
Classifier: Programming Language :: Python :: 3.9
Classifier: Programming Language :: Python :: 3.10
Requires-Python: >=3.7
License-File: LICENSE
Requires-Dist: gymnasium (~=0.26)
Requires-Dist: pybullet
Requires-Dist: numpy
Provides-Extra: dev
Requires-Dist: pytest ; extra == 'dev'
Requires-Dist: yapf ; extra == 'dev'
Requires-Dist: ipdb ; extra == 'dev'
Requires-Dist: glfw ; extra == 'dev'
